{
    "windowBackground": "#0f0f15",
    "primaryText": "#bac2de",
    "layerBackground1": "#BBC9C8",
    "layerBackground2": "#00B7BF",
    "layerBackground3": "#2D282E",
    "surfaceText": "#EAE0E7",
    "secondaryText": "#CFC3CD",
    "borderPrimary": "#BBC9C8",
    "shadowColor": "#000000",
    "accentPrimary": "#BBC9C8",
    "accentSecondary": "##BBC9C8",
    "selectionBackground": "#BBC9C8",
    "accentPrimaryText": "#FFFFFF",
    "selectionText": "#F2DCF3",
    "borderSecondary": "##CD3A91"
}